LICENSE
pyproject.toml
.github/README.md
source_agent/__init__.py
source_agent/entrypoint.py
source_agent/heavy.py
source_agent/orchestrator.py
source_agent/providers.py
source_agent/agents/__init__.py
source_agent/agents/code.py
source_agent/tools/__init__.py
source_agent/tools/calculator_tool.py
source_agent/tools/directory_create_tool.py
source_agent/tools/directory_delete_tool.py
source_agent/tools/file_delete_tool.py
source_agent/tools/file_list_tool.py
source_agent/tools/file_read_tool.py
source_agent/tools/file_search_tool.py
source_agent/tools/file_write_tool.py
source_agent/tools/get_current_date.py
source_agent/tools/msg_complete_tool.py
source_agent/tools/tool_registry.py
source_agent/tools/web_search_tool.py
source_agent-0.0.13.dist-info/METADATA
source_agent-0.0.13.dist-info/WHEEL
source_agent-0.0.13.dist-info/entry_points.txt
source_agent-0.0.13.dist-info/licenses/LICENSE
source_agent-0.0.13.dist-info/RECORD
