Metadata-Version: 2.4
Name: source-agent
Version: 0.0.13
Summary: Simple coding agent.
License-Expression: MIT
License-File: LICENSE
Classifier: Development Status :: 1 - Planning
Classifier: Environment :: Console
Classifier: Programming Language :: Python :: 3
Requires-Python: >=3.10
Requires-Dist: beautifulsoup4
Requires-Dist: ddgs
Requires-Dist: openai
Requires-Dist: pathspec
Requires-Dist: pyyaml
Requires-Dist: requests
Provides-Extra: developer
Requires-Dist: bandit[toml]; extra == 'developer'
Requires-Dist: black; extra == 'developer'
Requires-Dist: hatch; extra == 'developer'
Requires-Dist: mypy; extra == 'developer'
Requires-Dist: pytest; extra == 'developer'
Requires-Dist: pytest-cov; extra == 'developer'
Requires-Dist: ruff; extra == 'developer'
